deep_cross_attention/__init__.py
deep_cross_attention/dca_gpt.py
deep_cross_attention/gpt.py
deep_cross_attention-0.1.0.dist-info/METADATA
deep_cross_attention-0.1.0.dist-info/WHEEL
deep_cross_attention-0.1.0.dist-info/licenses/LICENSE
deep_cross_attention-0.1.0.dist-info/RECORD
