Metadata-Version: 2.4
Name: deep-cross-attention
Version: 0.1.0
Summary: Deep Cross Attention Language Model
Project-URL: Homepage, https://pypi.org/project/deep-cross-attention/
Project-URL: Repository, https://github.com/lucidrains/deep-cross-attention
Author-email: Phil Wang <lucidrains@gmail.com>
License: MIT License
License-File: LICENSE
Keywords: artificial intelligence,deep learning,residuals,transformers
Classifier: Development Status :: 4 - Beta
Classifier: Intended Audience :: Developers
Classifier: License :: OSI Approved :: MIT License
Classifier: Programming Language :: Python :: 3.9
Classifier: Topic :: Scientific/Engineering :: Artificial Intelligence
Requires-Python: >=3.9
Requires-Dist: einops>=0.8.0
Requires-Dist: einx>=0.3.0
Requires-Dist: rotary-embedding-torch
Requires-Dist: torch>=2.3
Provides-Extra: examples
Requires-Dist: tqdm; extra == 'examples'
Provides-Extra: test
Requires-Dist: pytest; extra == 'test'
